{
  "main": {
    "id": "1fc7b4a3b801b181",
    "type": "split",
    "children": [
      {
        "id": "ec5f2ce91ae4b693",
        "type": "tabs",
        "children": [
          {
            "id": "54bc7a0dfa1f5a3c",
            "type": "leaf",
            "state": {
              "type": "markdown",
              "state": {
                "file": "microservices/K8S.md",
                "mode": "source",
                "source": false
              }
            }
          }
        ]
      }
    ],
    "direction": "vertical"
  },
  "left": {
    "id": "8f50b166b4c24d0c",
    "type": "split",
    "children": [
      {
        "id": "201209c5c983b127",
        "type": "tabs",
        "children": [
          {
            "id": "770c954fb312f16e",
            "type": "leaf",
            "state": {
              "type": "file-explorer",
              "state": {
                "sortOrder": "alphabetical"
              }
            }
          },
          {
            "id": "634ea4781dc8bed6",
            "type": "leaf",
            "state": {
              "type": "search",
              "state": {
                "query": "dard",
                "matchingCase": false,
                "explainSearch": false,
                "collapseAll": false,
                "extraContext": false,
                "sortOrder": "alphabetical"
              }
            }
          },
          {
            "id": "1a526fbb6cf9ead5",
            "type": "leaf",
            "state": {
              "type": "bookmarks",
              "state": {}
            }
          }
        ]
      }
    ],
    "direction": "horizontal",
    "width": 300
  },
  "right": {
    "id": "4187709c3e689e1a",
    "type": "split",
    "children": [
      {
        "id": "d34c20a00ea1376e",
        "type": "tabs",
        "children": [
          {
            "id": "34661fb72c46ccfa",
            "type": "leaf",
            "state": {
              "type": "backlink",
              "state": {
                "file": "microservices/K8S.md",
                "collapseAll": false,
                "extraContext": false,
                "sortOrder": "alphabetical",
                "showSearch": false,
                "searchQuery": "",
                "backlinkCollapsed": false,
                "unlinkedCollapsed": true
              }
            }
          },
          {
            "id": "6c08d4d27f36cc1c",
            "type": "leaf",
            "state": {
              "type": "outgoing-link",
              "state": {
                "file": "microservices/K8S.md",
                "linksCollapsed": false,
                "unlinkedCollapsed": true
              }
            }
          },
          {
            "id": "cfcf527756b53061",
            "type": "leaf",
            "state": {
              "type": "tag",
              "state": {
                "sortOrder": "frequency",
                "useHierarchy": true
              }
            }
          },
          {
            "id": "16f1c019a7e1820a",
            "type": "leaf",
            "state": {
              "type": "outline",
              "state": {
                "file": "microservices/K8S.md"
              }
            }
          },
          {
            "id": "62856def8f637d93",
            "type": "leaf",
            "state": {
              "type": "all-properties",
              "state": {
                "sortOrder": "frequency",
                "showSearch": false,
                "searchQuery": ""
              }
            }
          }
        ],
        "currentTab": 4
      }
    ],
    "direction": "horizontal",
    "width": 200,
    "collapsed": true
  },
  "left-ribbon": {
    "hiddenItems": {
      "switcher:Open quick switcher": false,
      "graph:Open graph view": false,
      "canvas:Create new canvas": false,
      "daily-notes:Open today's daily note": false,
      "templates:Insert template": false,
      "command-palette:Open command palette": false
    }
  },
  "active": "54bc7a0dfa1f5a3c",
  "lastOpenFiles": [
    "Pasted image 20240303110624.png",
    "Pasted image 20240302161901.png",
    "Pasted image 20240123220651.png",
    "Pasted image 20240121214612.png",
    "Pasted image 20240121175321.png",
    "Pasted image 20240121175212.png",
    "microservices/CHALLENGES/SERVICE DISCOVERY.md",
    "microservices/K8S.md",
    "microservices/CHALLENGES/REACTIVE MICROSERVICES.md",
    "microservices/CHALLENGES/EDGE SERVER.md",
    "microservices/CHALLENGES/CONTROL LOOP.md",
    "microservices/CHALLENGES/CIRCUIT BREAKER.md",
    "microservices/CHALLENGES/CENTRALIZED MONITORING AND ALARMS.md",
    "microservices/CHALLENGES/CENTRAL CONFIGURATION.md",
    "microservices/CHALLENGES/CENTRALIZED LOG ANALYSIS.md",
    "microservices/CHALLENGES/AUTHORIZATION SERVER.md",
    "microservices/RESILIENT4J.md",
    "angular/OVERVIEW.md",
    "angular/Binding.md",
    "microservices/CHALLENGES/DISTRIBUTED TRACING.md",
    "microservices/CHALLENGES/CHALLENGES.md",
    "microservices/RABBIT MQ.md",
    "microservices/DOCKER.md",
    "microservices/FOOLISH BUG.md",
    "microservices/TESTING.md",
    "microservices/SPRINGBOOT 3.0.md",
    "unknown/Things i don't know.md",
    "microservices/CHƯA ĐƯỢC GIẢI QUYẾT.md",
    "angular/FRONT_END.md",
    "angular/FORM.md",
    "microservices/OAUTH2.md",
    "java",
    "microservices/CHALLENGES",
    "microservices/pictures/zimage 20230724201934.png",
    "microservices/pictures",
    "unknown",
    "Pasted image 20231010223719.png",
    "Pasted image 20230910231450.png",
    "Pasted image 20230910231133.png",
    "Pasted image 20230910231112.png",
    "angular"
  ]
}